undupe/__init__.py
undupe/preprocessing/__init__.py
undupe/preprocessing/preprocess_text.py
undupe/preprocessing/remove_duplicates.py
UnDupe-0.0.1.dist-info/LICENSE
UnDupe-0.0.1.dist-info/METADATA
UnDupe-0.0.1.dist-info/WHEEL
UnDupe-0.0.1.dist-info/top_level.txt
UnDupe-0.0.1.dist-info/RECORD
